whchat_template/__init__.py
whchat_template/apps.py
whchat_template/common.py
whchat_template/method.py
whchat_template/models.py
whchat_template/migrations/__init__.py
wechat_template-0.3.dist-info/METADATA
wechat_template-0.3.dist-info/WHEEL
wechat_template-0.3.dist-info/top_level.txt
wechat_template-0.3.dist-info/RECORD
