Metadata-Version: 2.1
Name: wechat-template
Version: 0.3
Summary: Django wx
Home-page: UNKNOWN
Author: yangcheng
Author-email: yangcheng.fan@yuemia.com
License: MIT
Platform: UNKNOWN
